bitalino.py
bitalino-1.2.6.dist-info/LICENSE.md
bitalino-1.2.6.dist-info/METADATA
bitalino-1.2.6.dist-info/WHEEL
bitalino-1.2.6.dist-info/top_level.txt
bitalino-1.2.6.dist-info/RECORD
