Metadata-Version: 2.1
Name: bitalino
Version: 1.2.6
Summary: revolution-python-api
Home-page: http://www.bitalino.com/
Download-URL: https://github.com/BITalinoWorld/revolution-python-api
Author: BITalinoWorld
Author-email: bitalino@plux.info
License: GNU GPL v3
Keywords: BITalino,Physiological Computing,Biosignal,Physiological Signal
Platform: UNKNOWN
Classifier: License :: OSI Approved :: GNU General Public License v3 or later (GPLv3+)
Classifier: Programming Language :: Python
Classifier: Programming Language :: Python :: 3.7
Classifier: Programming Language :: Python :: 3.8
Classifier: Programming Language :: Python :: 3.9
Classifier: Programming Language :: Python :: 3.10
Classifier: Topic :: Scientific/Engineering
Classifier: Topic :: Software Development :: Libraries
Requires-Python: >=3.7
License-File: LICENSE.md
